LICENSE
README.md
ckanext/__init__.py
ckanext/feedback/README.md
ckanext/feedback/__init__.py
ckanext/feedback/assets/css/admin.css
ckanext/feedback/assets/css/comment.css
ckanext/feedback/assets/css/details.css
ckanext/feedback/assets/css/edit.css
ckanext/feedback/assets/css/package_item.css
ckanext/feedback/assets/css/registration.css
ckanext/feedback/assets/css/resource_read.css
ckanext/feedback/assets/css/search.css
ckanext/feedback/assets/css/tooltip.css
ckanext/feedback/assets/js/aggregation.js
ckanext/feedback/assets/js/approval_and_delete.js
ckanext/feedback/assets/js/comment.js
ckanext/feedback/assets/js/detail.js
ckanext/feedback/assets/js/edit.js
ckanext/feedback/assets/js/moral_check_log.js
ckanext/feedback/assets/js/recaptcha.js
ckanext/feedback/assets/js/registration.js
ckanext/feedback/assets/js/resource_read.js
ckanext/feedback/assets/js/search.js
ckanext/feedback/assets/webassets.yml
ckanext/feedback/command/feedback.py
ckanext/feedback/components/comment.py
ckanext/feedback/controllers/__init__.py
ckanext/feedback/controllers/admin.py
ckanext/feedback/controllers/api/moral_check_log.py
ckanext/feedback/controllers/api/ranking.py
ckanext/feedback/controllers/cookie.py
ckanext/feedback/controllers/download.py
ckanext/feedback/controllers/pagination.py
ckanext/feedback/controllers/resource.py
ckanext/feedback/controllers/utilization.py
ckanext/feedback/i18n/.gitkeep
ckanext/feedback/i18n/ja/LC_MESSAGES/ckanext-feedback.mo
ckanext/feedback/i18n/ja/LC_MESSAGES/ckanext-feedback.po
ckanext/feedback/migration/feedback/alembic.ini
ckanext/feedback/migration/feedback/env.py
ckanext/feedback/migration/feedback/script.py.mako
ckanext/feedback/migration/feedback/versions/000_40bf9a900ef5_init.py
ckanext/feedback/migration/feedback/versions/001_2a8c621c22c8_.py
ckanext/feedback/migration/feedback/versions/002_b883d604a877_.py
ckanext/feedback/migration/feedback/versions/003_4c5922f300d6_.py
ckanext/feedback/migration/feedback/versions/004_8ae77eb847cd_.py
ckanext_feedback-1.4.6.dist-info/METADATA
ckanext_feedback-1.4.6.dist-info/WHEEL
ckanext_feedback-1.4.6.dist-info/entry_points.txt
ckanext_feedback-1.4.6.dist-info/licenses/LICENSE
ckanext_feedback-1.4.6.dist-info/RECORD
