Metadata-Version: 2.4
Name: ckanext-feedback
Version: 1.4.6
Summary: The extension to feedback on CKAN datasets such as review, number of downloads,use-cases,resolved-problems, and way of use
License: AGPL-3.0
License-File: LICENSE
Keywords: ckan,ckan extension,opendata,open-data,review
Author: C3Lab
Author-email: info.c3lab@gmail.com
Requires-Python: >=3.9,<4.0
Classifier: Development Status :: 4 - Beta
Classifier: License :: OSI Approved :: GNU Affero General Public License v3
Classifier: License :: OSI Approved :: GNU Affero General Public License v3 or later (AGPLv3+)
Classifier: Programming Language :: Python :: 3
Classifier: Programming Language :: Python :: 3.9
Classifier: Programming Language :: Python :: 3.10
Classifier: Programming Language :: Python :: 3.11
Classifier: Programming Language :: Python :: 3.12
Classifier: Programming Language :: Python :: 3.13
Classifier: Programming Language :: Python :: 3.14
Classifier: Programming Language :: Python :: 3.8
Requires-Dist: pandas (>=2.3.2,<3.0.0)
Requires-Dist: psycopg2 (==2.9.3)
Requires-Dist: sqlalchemy (>=1.3.5,<2.0.0)
Requires-Dist: xlsxwriter (>=3.2.9,<4.0.0)
Project-URL: Documentation, https://github.com/c-3lab/ckanext-feedback/README.md
Project-URL: Repository, https://github.com/c-3lab/ckanext-feedback/
